sconekc/__init__.py
sconekc/sconekc.py
sconekc-0.1.2.dist-info/METADATA
sconekc-0.1.2.dist-info/WHEEL
sconekc-0.1.2.dist-info/top_level.txt
sconekc-0.1.2.dist-info/RECORD
